atomica/__init__.py
atomica/calibration.py
atomica/cascade.py
atomica/data.py
atomica/demos.py
atomica/excel.py
atomica/framework.py
atomica/function_parser.py
atomica/migration.py
atomica/model.py
atomica/optimization.py
atomica/parameters.py
atomica/plotting.py
atomica/programs.py
atomica/project.py
atomica/reconciliation.py
atomica/results.py
atomica/scenarios.py
atomica/system.py
atomica/utils.py
atomica/version.py
atomica/yaml_calibration.py
atomica/library/cervicalcancer_databook.xlsx
atomica/library/cervicalcancer_framework.xlsx
atomica/library/cervicalcancer_progbook.xlsx
atomica/library/combined_databook.xlsx
atomica/library/combined_framework.xlsx
atomica/library/combined_progbook.xlsx
atomica/library/diabetes_databook.xlsx
atomica/library/diabetes_framework.xlsx
atomica/library/diabetes_progbook.xlsx
atomica/library/dt_databook.xlsx
atomica/library/dt_framework.xlsx
atomica/library/framework_template.xlsx
atomica/library/framework_template_advanced.xlsx
atomica/library/hiv_databook.xlsx
atomica/library/hiv_dyn_databook.xlsx
atomica/library/hiv_dyn_framework.xlsx
atomica/library/hiv_dyn_progbook.xlsx
atomica/library/hiv_framework.xlsx
atomica/library/hiv_progbook.xlsx
atomica/library/hypertension_databook.xlsx
atomica/library/hypertension_dyn_databook.xlsx
atomica/library/hypertension_dyn_framework.xlsx
atomica/library/hypertension_dyn_progbook.xlsx
atomica/library/hypertension_framework.xlsx
atomica/library/hypertension_progbook.xlsx
atomica/library/malaria_framework.xlsx
atomica/library/service_databook.xlsx
atomica/library/service_framework.xlsx
atomica/library/sir_databook.xlsx
atomica/library/sir_framework.xlsx
atomica/library/sir_progbook.xlsx
atomica/library/sir_vaccine_databook.xlsx
atomica/library/sir_vaccine_framework.xlsx
atomica/library/tb_databook.xlsx
atomica/library/tb_framework.xlsx
atomica/library/tb_progbook.xlsx
atomica/library/tb_progbook_defaults.xlsx
atomica/library/tb_simple_databook.xlsx
atomica/library/tb_simple_dyn_databook.xlsx
atomica-1.31.3.dist-info/licenses/LICENSE
atomica-1.31.3.dist-info/METADATA
atomica-1.31.3.dist-info/WHEEL
atomica-1.31.3.dist-info/top_level.txt
atomica-1.31.3.dist-info/RECORD
