Metadata-Version: 2.4
Name: atomica
Version: 1.31.3
Summary: Toolbox for compartment-based dynamic systems with costing and optimization
Author-email: Atomica Team <info@atomica.tools>
License: MIT
Project-URL: Homepage, https://atomica.tools
Keywords: dynamic,compartment,optimization,disease
Classifier: Environment :: Console
Classifier: Intended Audience :: Science/Research
Classifier: License :: OSI Approved :: MIT License
Classifier: Operating System :: OS Independent
Classifier: Programming Language :: Python
Classifier: Topic :: Software Development :: Libraries :: Python Modules
Classifier: Development Status :: 5 - Production/Stable
Classifier: Programming Language :: Python :: 3.7
Classifier: Programming Language :: Python :: 3.8
Classifier: Programming Language :: Python :: 3.9
Classifier: Programming Language :: Python :: 3.10
Classifier: Programming Language :: Python :: 3.11
Classifier: Programming Language :: Python :: 3.12
Classifier: Programming Language :: Python :: 3.13
Requires-Python: >=3.7
License-File: LICENSE
Requires-Dist: matplotlib
Requires-Dist: numpy>=1.10.1
Requires-Dist: scipy>=1.6
Requires-Dist: pandas
Requires-Dist: xlsxwriter
Requires-Dist: openpyxl
Requires-Dist: pyswarm
Requires-Dist: hyperopt
Requires-Dist: sciris
Requires-Dist: tqdm
Dynamic: license-file
